spotzero/__init__.py
spotzero/cli.py
spotzero/dbus_handler.py
spotzero/linux.py
spotzero-0.1.1.dist-info/LICENSE
spotzero-0.1.1.dist-info/METADATA
spotzero-0.1.1.dist-info/WHEEL
spotzero-0.1.1.dist-info/entry_points.txt
spotzero-0.1.1.dist-info/top_level.txt
spotzero-0.1.1.dist-info/RECORD
