Metadata-Version: 2.1
Name: spotzero
Version: 0.1.1
Summary: control the spotify app with a cli or with a package
License-File: LICENSE
Requires-Dist: dbus-python ==1.3.2
Requires-Dist: click >=8.1
